LICENSE
README.rst
setup.py
BLACKFORGE004/FORGE.py
BLACKFORGE004/__init__.py
BLACKFORGE004.egg-info/PKG-INFO
BLACKFORGE004.egg-info/SOURCES.txt
BLACKFORGE004.egg-info/dependency_links.txt
BLACKFORGE004.egg-info/requires.txt
BLACKFORGE004.egg-info/top_level.txt